LICENSE.txt
MANIFEST.in
README.rst
setup.py
cmsplugin_getthecode/__init__.py
cmsplugin_getthecode/cms_plugins.py
cmsplugin_getthecode/models.py
cmsplugin_getthecode.egg-info/PKG-INFO
cmsplugin_getthecode.egg-info/SOURCES.txt
cmsplugin_getthecode.egg-info/dependency_links.txt
cmsplugin_getthecode.egg-info/not-zip-safe
cmsplugin_getthecode.egg-info/requires.txt
cmsplugin_getthecode.egg-info/top_level.txt
cmsplugin_getthecode/migrations/0001_initial.py
cmsplugin_getthecode/migrations/0002_auto_20161025_2002.py
cmsplugin_getthecode/migrations/__init__.py