Metadata-Version: 1.1
Name: cmsplugin-getthecode
Version: 0.1.0
Summary: Get The Code Plugin for django CMS
Home-page: https://github.com/FabriceSalvaire/cmsplugin-getthecode
Author: Fabrice Salvaire
Author-email: fabrice.salvaire@orange.fr
License: LICENSE.txt
Platform: OS Independent
Classifier: Development Status :: 5 - Production/Stable
Classifier: Environment :: Web Environment
Classifier: Framework :: Django
Classifier: Intended Audience :: Developers
Classifier: License :: OSI Approved :: BSD License
Classifier: Operating System :: OS Independent
Classifier: Programming Language :: Python
Classifier: Programming Language :: Python :: 3.4
Classifier: Programming Language :: Python :: 3.5
Classifier: Topic :: Internet :: WWW/HTTP :: Dynamic Content
Classifier: Topic :: Software Development
